{
    "@class": "com.kony.gen.viz.model.component.KVizRichText",
    "DNDConfig": null,
    "_height_": {
        "type": "string",
        "value": "33dp"
    },
    "_left_": {
        "type": "string",
        "value": "152dp"
    },
    "_margin_": [
        0,
        0,
        0,
        0
    ],
    "_padding_": [
        0,
        0,
        0,
        0
    ],
    "_skin_": "s98613a69cab4110839dec7aaa02d794",
    "_text_": "KFC Fried Chicken",
    "_top_": {
        "type": "string",
        "value": "143dp"
    },
    "_width_": {
        "type": "string",
        "value": "50.26%"
    },
    "_wrapping_": 2,
    "canUpdateUI": true,
    "containerweight": 100,
    "contentalignment": 4,
    "id": "RichText0h3d608e21f1c49",
    "info": null,
    "iscustomlayout": false,
    "isvisible": true,
    "kuid": "e6d83dd04938438aa1005e4a3c3f76e4",
    "linkskin": "s69d0adfe99243bf9519f028512b07b7",
    "name": "kony.ui.RichText",
    "parent": "Form10",
    "pf": "Form10",
    "retaincontentalignment": false,
    "retainflexpositionproperties": false,
    "wType": "RichText",
    "widgetalignment": 5,
    "zindex": 1
}