{
    "@class": "com.kony.gen.viz.model.component.KVizRichText",
    "DNDConfig": null,
    "_height_": {
        "type": "string",
        "value": "60dp"
    },
    "_left_": {
        "type": "string",
        "value": "75dp"
    },
    "_margin_": [
        0,
        0,
        0,
        0
    ],
    "_padding_": [
        0,
        0,
        0,
        0
    ],
    "_skin_": "s4055b5cb189469abcba7c86daf08b0b",
    "_text_": "We focus a lot on helping the first time or inexperienced traveler head out",
    "_top_": {
        "type": "string",
        "value": "70dp"
    },
    "_width_": {
        "type": "string",
        "value": "71.27%"
    },
    "_wrapping_": 2,
    "canUpdateUI": true,
    "containerweight": 100,
    "contentalignment": 4,
    "id": "RichText0b3e30d99b81c4d",
    "info": null,
    "iscustomlayout": false,
    "isvisible": true,
    "kuid": "c26c56c96164445aa71bafdf1cfdbae9",
    "linkskin": "s69d0adfe99243bf9519f028512b07b7",
    "name": "kony.ui.RichText",
    "parent": "Form7",
    "pf": "Form7",
    "retaincontentalignment": false,
    "retainflexpositionproperties": false,
    "wType": "RichText",
    "widgetalignment": 5,
    "zindex": 2
}